[
  {
    "id": "3",
    "ts": "12.07.2024 23:01:33",
    "photo": "photos/photo_2@12-07-2024_23-01-33.jpg",
    "text": "袨褎褨褑褨泄薪芯! 袧邪褉械褕褌褨 胁 袚械褉褨 屑芯卸薪邪 泻褉邪褋懈胁芯 褌邪 褋屑邪褔薪芯 胁褨写褋胁褟褌泻褍胁邪褌懈 写懈褌褟褔褨 写薪褨 薪邪褉芯写卸械薪薪褟 胁 褉械褋褌芯褉邪薪褨 胁 褑械薪褌褉褨 屑褨褋褌邪! 孝邪泻芯卸 屑芯卸薪邪 蟹邪屑芯胁懈褌懈 写褍卸械 褋屑邪褔薪褨 褌邪 泻褉邪褋懈胁褨 褌芯褉褌懈泻懈 褨 写械褋械褉褌懈, 褟泻 屑懈 蟹胁懈泻谢懈 胁 校泻褉邪褩薪褨 馃挋馃挍"
  },
  {
    "id": "5",
    "ts": "13.07.2024 14:10:34",
    "photo": "photos/photo_4@13-07-2024_14-10-34.jpg",
    "text": "袧邪泄褋屑邪褔薪褨褕褨 薪邪褔懈薪泻懈! 效械褉胁芯薪懈泄 袨泻褋邪屑懈褌, 小薪褨泻械褉褋, 袩芯褌褉褨泄薪懈泄 褕芯泻芯谢邪写, 袧邪锌芯谢械芯薪, 袦械写褨胁薪懈泻, 袧褜褞 袡芯褉泻, 袛懈褌褟褔懈泄 褌芯褉褌懈泻.\n笑褨薪邪 25 褦胁褉芯/泻谐 蟹褨 褋褌邪薪写邪褉褌薪懈屑 写械泻芯褉芯屑."
  },
  {
    "id": "76",
    "ts": "13.07.2024 18:00:56",
    "photo": "photos/photo_13@13-07-2024_18-00-56.jpg",
    "text": "袙邪褕褨 胁褨写谐褍泻懈 鉂わ笍鉂わ笍鉂わ笍"
  },
  {
    "id": "190",
    "ts": "14.07.2024 09:25:40",
    "photo": "photos/photo_20@14-07-2024_09-25-40.jpg",
    "text": "袙褋褨屑 写芯斜褉芯谐芯 褉邪薪泻褍 褌邪 锌褉懈褦屑薪芯谐芯 胁懈褏褨写薪芯谐芯!"
  },
  {
    "id": "193",
    "ts": "14.07.2024 10:09:23",
    "photo": "photos/photo_21@14-07-2024_10-09-23.jpg",
    "text": "袩褉懈泄屑邪褦屑芯 褨薪写懈胁褨写褍邪谢褜薪褨 蟹邪屑芯胁谢械薪薪褟 薪邪 褌芯褉褌懈泻懈 褌邪 锌芯褉褑褨泄薪褨 写械褋械褉褌懈. 小邪屑芯胁懈胁褨蟹 蟹 褉械褋褌芯褉邪薪褍 1880 ABACO 胁 褑械薪褌褉褨 袚械褉懈.\n笑褨薪邪 25 褦胁褉芯/泻谐 蟹褨 褋褌邪薪写邪褉褌薪懈屑 写械泻芯褉芯屑 (薪邪锌懈褋, 褕邪锌芯褔泻懈 蟹 泻褉械屑褍). 袙械褋褜 褨薪褕懈泄 写械泻芯褉 褋锌谢邪褔褍褦褌褜褋褟 锌芯 褔械泻褍.\n袟邪屑芯胁谢械薪薪褟 锌褉懈泄屑邪褦屑芯 屑褨薪褨屑褍屑 蟹邪 3 写薪褨. \n袛谢褟 蟹邪屑芯胁谢械薪薪褟 锌懈褕褨褌褜 "
  },
  {
    "id": "231",
    "ts": "15.07.2024 08:49:45",
    "photo": "photos/photo_31@15-07-2024_08-49-45.jpg",
    "text": "袙褋褨屑 写芯斜褉芯谐芯 褉邪薪泻褍!\n袧邪谐邪写褍褞, 褖芯 屑懈 胁卸械 锌褉邪褑褞褦屑芯! \n袧褨卸薪褨, 褋屑邪褔薪褨, 泻褉邪褋懈胁褨 褌芯褉褌懈泻懈 屑芯卸薪邪 蟹邪屑芯胁懈褌懈 锌褉褟屑芯 蟹邪褉邪蟹 馃┓"
  },
  {
    "id": "236",
    "ts": "15.07.2024 13:18:31",
    "photo": "photos/photo_32@15-07-2024_13-18-31.jpg",
    "text": "袧邪泄褋屑邪褔薪褨褕械 锌械褔懈胁芯 褍 薪邪褋 馃崻\n袉写械邪谢褜薪芯 薪邪 写械薪褜 薪邪褉芯写卸械薪薪褟 胁 褋邪写芯褔芯泻, 褕泻芯谢褍, 薪邪 写懈褌褟褔械 写芯屑邪褕薪褦 褋胁褟褌芯 邪斜芯 锌褉芯褋褌芯 锌芯谢邪褋褍胁邪褌懈 褉芯写懈薪芯褞 馃槆\n袗屑械褉懈泻邪薪褋褜泻械 锌械褔懈胁芯 蟹 M&Ms. 袦始褟泻械, 屑械谐邪 褋屑邪褔薪械, 蟹 褕芯泻芯谢邪写薪懈屑懈 泻褉邪锌谢褟屑懈 褌邪 写褉邪卸械. \n笑褨薪邪 15 褦胁褉芯/泻谐. 袧邪 1 泻谐 褨写械 ~ 40 褕褌.\n袦邪褉屑褍褉芯胁械 褕芯泻芯谢邪写薪械 锌械褔懈胁芯. 袙"
  },
  {
    "id": "256",
    "ts": "16.07.2024 09:53:13",
    "photo": "photos/photo_42@16-07-2024_09-53-13.jpg",
    "text": "袙褋褨屑 写芯斜褉芯谐芯 褉邪薪泻褍 馃尀"
  },
  {
    "id": "271",
    "ts": "16.07.2024 13:01:49",
    "photo": "photos/photo_44@16-07-2024_13-01-49.jpg",
    "text": "袩褉懈泄屑邪褦屑芯 褌械褉屑褨薪芯胁褨 蟹邪屑芯胁谢械薪薪褟 薪邪 泻邪锌泻械泄泻懈 馃 \n袆 3 胁懈写懈:\n袘褉邪褍薪褨 蟹 薪褍褌械谢谢芯褞\n袙邪薪褨谢褜薪褨 写邪斜谢-褔褨蟹 蟹 褎褉褍泻褌芯胁懈屑 泻芯薪褎褨褌褞褉芯屑\n袦芯褉泻芯胁薪褨 褨蟹 褋芯谢芯薪芯褞 泻邪褉邪屑械谢谢褞.\n笑褨薪邪 12 褦胁褉芯/6 褕褌 蟹褨 褋褌邪薪写邪褉褌薪懈屑 写械泻芯褉芯屑.\n袟邪屑芯胁懈褌懈 屑芯卸薪邪 6/9/12 褨 褌写 褕褌褍泻)\n袙芯薪懈 褋褌邪薪褍褌褜 褔褍写芯胁懈屑 写芯锌芯胁薪械薪薪褟屑 胁邪褕芯谐芯 泻械薪写褨斜邪褉褍 褌邪 褨写械邪谢"
  },
  {
    "id": "284",
    "ts": "16.07.2024 21:50:22",
    "photo": "photos/photo_54@16-07-2024_21-50-22.jpg",
    "text": "楔邪薪芯胁薪褨 写褉褍蟹褨!\n袙卸械 褑褨褦褩 褋褍斜芯褌懈 胁懈 蟹屑芯卸械褌械 褋泻褍褕褌褍胁邪褌懈 写械褟泻褨 薪邪褕褨 写械褋械褉褌懈 胁 褉械褋褌芯褉邪薪褨 1880 ABACO 蟹邪 邪泻褑褨泄薪芯褞 褑褨薪芯褞!\n袟 15:00 薪邪 谢褨褌薪褨泄 褌械褉邪褋褨 屑懈 蟹邪锌褉芯锌芯薪褍褦屑芯 袙邪屑 效械褉胁芯薪懈泄 袨泻褋邪屑懈褌, 小薪褨泻械褉褋, 泻谢邪褋懈褔薪懈泄 效褨蟹泻械泄泻, 屑褍褋芯胁懈泄 写械褋械褉褌 孝褉懈 楔芯泻芯谢邪写懈 褌邪 薪邪泄褋屑邪褔薪褨褕械 锌械褔懈胁芯 馃崻 \n袣邪胁褍, 褔邪泄 褌邪 褋芯泻 褌邪泻芯"
  },
  {
    "id": "297",
    "ts": "17.07.2024 08:31:32",
    "photo": "photos/photo_60@17-07-2024_08-31-32.jpg",
    "text": "袙褋褨屑 写芯斜褉芯谐芯 褉邪薪泻褍!\n小谢褨写泻褍泄褌械 蟹邪 薪邪褕芯褞 谐褉褍锌芯褞. 小褜芯谐芯写薪褨 胁懈泻谢邪写械屑芯 胁褨写械芯 褌邪 褎芯褌芯 薪邪褕芯谐芯 蟹邪谢褍 写谢褟 写懈褌褟褔懈褏 褋胁褟褌!"
  },
  {
    "id": "322",
    "ts": "18.07.2024 08:18:58",
    "photo": "photos/photo_61@18-07-2024_08-18-58.jpg",
    "text": "袙褋褨屑 写芯斜褉芯谐芯 褉邪薪泻褍! Und sch枚nen Tag 馃尀"
  },
  {
    "id": "328",
    "ts": "18.07.2024 18:46:22",
    "photo": "photos/photo_62@18-07-2024_18-46-22.jpg",
    "text": "小褜芯谐芯写薪褨 胁褨写写邪胁邪谢懈 泻芯褉芯斜芯褔泻褍 褋芯谢芯写械薪褜泻芯谐芯 馃崻馃槝"
  },
  {
    "id": "336",
    "ts": "19.07.2024 08:13:53",
    "photo": "photos/photo_64@19-07-2024_08-13-53.jpg",
    "text": "袛芯斜褉芯谐芯 褉邪薪泻褍 胁褋褨屑!"
  },
  {
    "id": "349",
    "ts": "20.07.2024 15:28:40",
    "photo": "photos/photo_65@20-07-2024_15-28-40.jpg",
    "text": "袧邪褕邪 胁褨褌褉懈薪邪 谐芯褌芯胁邪 鉂わ笍\n袛褍卸械 褋屑邪褔薪褨 褌芯褉褌懈泻懈, 泻邪锌泻械泄泻懈 褌邪 锌械褔懈胁芯! 袗泻褑褨泄薪褨 褑褨薪懈!\n袪械褋褌芯褉邪薪 锌褉邪褑褞褦 写芯 23:00, 邪谢械 泻褨谢褜泻褨褋褌褜 写械褋械褉褌褨胁 芯斜屑械卸械薪邪!\n1880 ABACO \nStadtgraben 14, 07545 Gera"
  },
  {
    "id": "365",
    "ts": "21.07.2024 11:32:42",
    "photo": "photos/photo_71@21-07-2024_11-32-42.jpg",
    "text": "袙褋褨屑 写芯斜褉芯谐芯 褉邪薪泻褍!\n袣芯屑褍 褌邪泻芯卸 卸邪褉泻芯, 褟泻 褨 薪邪屑, 泻懈写邪褞 泻谢邪褋薪褍 谢芯泻邪褑褨褞!\n袩褉懈褉芯写薪褨泄 斜邪褋械泄薪 Kaimberg. \n笑械 芯蟹械褉芯, 写械 褦 谢芯泻邪褑褨褟 蟹 锌褨褋芯褔泻芯屑 写谢褟 写褨褌芯泻, 谢芯泻邪褑褨褟 写谢褟 锌谢邪胁褑褨胁, 斜邪褋械泄薪 写谢褟 蟹芯胁褋褨屑 泻邪褉邪锌褍蟹懈泻褨胁. 袆 褌褨薪褜. \n袙褏褨写 3,5 褦胁褉芯. 袟邪 褋芯褑 泻邪褉褌泻芯褞 2 褦胁褉芯.\n\nKaimberger Str., 07551 Gera"
  },
  {
    "id": "369",
    "ts": "21.07.2024 14:46:32",
    "photo": "photos/photo_65@20-07-2024_15-28-40.jpg",
    "text": "孝邪泻芯卸 胁 薪邪褟胁薪芯褋褌褨 褦 褌褉芯褕泻懈 锌械褔懈胁邪. 袉写械邪谢褜薪芯 薪邪 写懈褌褟褔械 褋胁褟褌芯 写芯写芯屑褍 邪斜芯 胁 褋邪写芯褔芯泻!\n袦芯卸薪邪 蟹邪斜褉邪褌懈 褋褜芯谐芯写薪褨 锌褨褋谢褟 18:00"
  },
  {
    "id": "384",
    "ts": "22.07.2024 08:33:52",
    "photo": "photos/photo_81@22-07-2024_08-33-52.jpg",
    "text": "袙褋褨屑 写芯斜褉芯谐芯 褉邪薪泻褍 褌邪 胁写邪谢芯谐芯 写薪褟!"
  },
  {
    "id": "385",
    "ts": "22.07.2024 13:13:05",
    "photo": "photos/photo_82@22-07-2024_13-13-05.jpg",
    "text": "袨褋褜 褌邪泻械 褋胁褟褌芯 斜褍谢芯 褍 薪邪褋 胁 褋褍斜芯褌褍 胁 褉械褋褌芯褉邪薪褨 1880 ABACO. 袙懈 锌芯谐谢褟薪褜褌械 褟泻械 屑械薪褞 锌褉芯锌芯薪褍褞褌褜 写谢褟 写褨褌芯泻! 袉 褑械 胁褋械 蟹邪 10-15 褦胁褉芯 蟹 写懈褌懈薪泻懈!\n袟胁械褉褌邪泄褌械褋褜 写芯 薪邪褋 褨 屑懈 胁谢邪褕褌褍褦屑芯 胁邪屑 泻褉褍褌械 褋胁褟褌芯 蟹 泻械薪写褨斜邪褉芯屑, 写懈褌褟褔懈屑 屑械薪褞 褌邪 褎芯褌芯蟹芯薪芯褞!"
  },
  {
    "id": "399",
    "ts": "23.07.2024 11:14:58",
    "photo": "photos/photo_90@23-07-2024_11-14-58.jpg",
    "text": "袙褋褨屑 写芯斜褉芯谐芯 写薪褟!"
  },
  {
    "id": "409",
    "ts": "23.07.2024 21:19:30",
    "photo": "photos/photo_98@23-07-2024_21-19-30.jpg",
    "text": "小锌邪褋懈斜芯 斜芯谢褜褕芯械 蟹邪 芯褌蟹褘胁!\n携 褍褋锌械谢邪 褋写械谢邪褌褜 褎芯褌芯 胁邪褕械谐芯 薪邪斜芯褉邪))"
  },
  {
    "id": "410",
    "ts": "24.07.2024 12:21:53",
    "photo": "photos/photo_99@24-07-2024_12-21-53.jpg",
    "text": "袙褋褨屑 锌褉懈褦屑薪芯谐芯 写薪褟!"
  },
  {
    "id": "414",
    "ts": "25.07.2024 08:24:47",
    "photo": "photos/photo_103@25-07-2024_08-24-47.jpg",
    "text": "袙褋褨屑 写芯斜褉芯谐芯 褉邪薪泻褍!"
  },
  {
    "id": "417",
    "ts": "25.07.2024 16:05:26",
    "photo": "photos/photo_104@25-07-2024_16-05-26.jpg",
    "text": "袙 薪邪褟胁薪芯褋褌褨! 袦芯卸薪邪 蟹邪斜褉邪褌懈 锌褉褟屑芯 蟹邪褉邪蟹!\n袧械泄屑芯胁褨褉薪懈泄 芯褋芯斜谢懈胁懈泄 袦械写褨胁薪懈泻. 袟 薪邪泄薪褨卸薪褨褕懈屑 泻褉械屑芯屑 馃い\n袙邪谐邪 斜褨谢褟 1 泻谐. 袗泻褑褨泄薪邪 褑褨薪邪 20 褦胁褉芯! 袣芯屑褍?)\n孝邪泻芯卸 屑芯卸薪邪 蟹邪屑芯胁懈褌懈 薪邪 褑褞 褋褍斜芯褌褍 袦械写褨胁薪懈泻 1-2 泻谐. \n袩懈褕褨褌褜 胁 锌褉懈胁邪褌 馃憠"
  },
  {
    "id": "418",
    "ts": "25.07.2024 16:47:11",
    "photo": "photos/photo_105@25-07-2024_16-47-11.jpg",
    "text": "袦械写褨胁薪懈泻 锌褉芯写邪薪芯鉂楋笍鉂楋笍鉂楋笍\n袧邪 褋褍斜芯褌褍 屑芯卸薪邪 蟹邪屑芯胁懈褌懈 锌芯 20 褦胁褉芯/泻谐!\n孝邪泻芯卸 锌褉懈泄屑邪褦屑芯 蟹邪屑芯胁谢械薪薪褟 薪邪 褑褞 褋褍斜芯褌褍 薪邪 褎褉邪薪褑褍蟹褜泻懈泄 肖褉械蟹始褦!\n25 褦胁褉芯 泻褨谢芯谐褉邪屑芯胁懈泄 褌芯褉褌懈泻."
  },
  {
    "id": "422",
    "ts": "25.07.2024 17:08:03",
    "photo": "photos/photo_108@25-07-2024_17-08-03.jpg",
    "text": "袧邪褕邪 胁褨褌褉懈薪邪 褋褜芯谐芯写薪褨 ! 袧械褉械邪谢褜薪芯 褋屑邪褔薪褨 褌芯褉褌懈 褌邪 写械褋械褉褌懈! 袩谢褞褋 褋屑邪褔薪械 写芯屑邪褕薪褦 褨褋锌邪薪褋褜泻械 胁懈薪芯 锌芯 3 褦胁褉芯 蟹邪 斜芯泻邪谢 褌褨谢褜泻懈 褋褜芯谐芯写薪褨! 袧邪 谢褨褌薪褨泄 褌械褉邪褋褨!\n袣褨谢褜泻褨褋褌褜 写械褋械褉褌褨胁 芯斜屑械卸械薪邪!\n袗写褉械褋邪 薪邪褕芯谐芯 褉械褋褌芯褉邪薪褍: Stadtgraben 14, 07545 Gera"
  },
  {
    "id": "428",
    "ts": "26.07.2024 09:41:38",
    "photo": "photos/photo_113@26-07-2024_09-41-38.jpg",
    "text": ""
  },
  {
    "id": "435",
    "ts": "27.07.2024 10:25:07",
    "photo": "photos/photo_117@27-07-2024_10-25-07.jpg",
    "text": "袙褋褨屑 写芯斜褉芯谐芯 褉邪薪泻褍 褌邪 锌褉懈褦屑薪芯褩 褋褍斜芯褌懈!"
  },
  {
    "id": "456",
    "ts": "27.07.2024 17:19:03",
    "photo": "photos/photo_120@27-07-2024_17-19-03.jpg",
    "text": "袙 袧袗携袙袧袨小孝袉! 袟邪斜褉邪褌懈 褑褨谢懈屑 屑芯卸薪邪 锌褉芯褌褟谐芯屑 15 褏胁懈谢懈薪. 袩芯褌褨屑 胁懈褋褌邪胁谢褟褦屑芯 薪邪 胁褨褌褉懈薪褍 - 胁褨薪 写褍卸械 锌芯锌褍谢褟褉薪懈泄!\n肖褉邪薪褑褍蟹褜泻懈泄 谢械谐泻懈泄 褌芯褉褌懈泻 肖褉械蟹始褦. 笑褨薪邪 25 褦胁褉芯. 袙邪谐邪 斜褨谢褟 1 泻谐.\n袦懈 蟹薪邪褏芯写懈屑芯褋褜 胁 褑械薪褌褉褨 袚械褉懈. 袪械褋褌芯褉邪薪 1880 ABACO.\nStadtgraben 14, 07545 Gera\n袛谢褟 蟹邪屑芯胁谢械薪薪褟 锌懈褕褨褌褜 胁 锌褉懈胁邪褌"
  },
  {
    "id": "457",
    "ts": "27.07.2024 18:27:11",
    "photo": "photos/photo_120@27-07-2024_17-19-03.jpg",
    "text": "袧邪褕 肖褉械蟹始褦 薪邪 胁褨褌褉懈薪褨!\n孝邪泻芯卸 胁 薪邪褟胁薪芯褋褌褨 楔胁邪褉褑胁邪谢褜写褋褜泻懈泄 褌芯褉褌 褌邪 袘褉邪褍薪褨. 袩褉懈褏芯写褜褌械! 袦芯卸薪邪 锌芯褋懈写褨褌懈 薪邪 褌械褉邪褋褨 邪斜芯 蟹邪斜褉邪褌懈 褋屑邪泻芯谢懈泻懈 褨蟹 褋芯斜芯褞!\n1880 ABACO\nStadtgraben 14, 07545 Gera"
  },
  {
    "id": "466",
    "ts": "28.07.2024 09:08:19",
    "photo": "photos/photo_126@28-07-2024_09-08-19.jpg",
    "text": "袙褋褨屑 写芯斜褉芯谐芯 褉邪薪泻褍 褌邪 褔褍写芯胁芯褩 薪械写褨谢褨!"
  },
  {
    "id": "473",
    "ts": "28.07.2024 13:19:18",
    "photo": "photos/photo_129@28-07-2024_09-10-44.jpg",
    "text": "楔邪薪芯胁薪褨 泻谢褨褦薪褌懈!\n袧邪 薪邪褋褌褍锌薪懈泄 褌懈卸写械薪褜 屑芯卸械屑芯 胁蟹褟褌懈 褖械 泻褨谢褜泻邪 褌芯褉褌懈泻褨胁!\n袧邪锌芯谢械芯薪 20 褦胁褉芯/泻谐\n袘褨褋泻胁褨褌薪褨 蟹 褉褨蟹薪芯屑邪薪褨褌薪懈屑懈 薪邪褔懈薪泻邪屑懈-25 褦胁褉芯/泻谐\n袣邪锌泻械泄泻懈 15 褦胁褉芯/6 褕褌\n袩谢邪薪褍泄褌械 褋胁芯褩 蟹邪屑芯胁谢械薪薪褟 屑褨薪褨屑褍屑 蟹邪 3 写薪褨, 斜褍写褜 谢邪褋泻邪 馃檹"
  },
  {
    "id": "486",
    "ts": "29.07.2024 09:52:51",
    "photo": "photos/photo_138@29-07-2024_09-52-51.jpg",
    "text": "袙褋褨屑 写芯斜褉芯谐芯 褉邪薪泻褍 褌邪 锌褉懈褦屑薪芯谐芯 写薪褟!"
  },
  {
    "id": "493",
    "ts": "30.07.2024 09:02:40",
    "photo": "photos/photo_139@30-07-2024_09-02-40.jpg",
    "text": "袙褋褨屑 写芯斜褉芯谐芯 褉邪薪泻褍!"
  },
  {
    "id": "496",
    "ts": "30.07.2024 19:59:49",
    "photo": "photos/photo_140@30-07-2024_19-59-49.jpg",
    "text": "袛褍卸械 写褟泻褍褦屑芯 蟹邪 胁邪褕褍 写芯胁褨褉褍 褌邪 胁邪褕褨 蟹邪屑芯胁谢械薪薪褟!"
  },
  {
    "id": "503",
    "ts": "31.07.2024 08:23:40",
    "photo": "photos/photo_144@31-07-2024_08-23-40.jpg",
    "text": "袙褋褨屑 写芯斜褉芯谐芯 褉邪薪泻褍 褌邪 胁写邪谢芯褩 褋械褉械写懈 馃"
  },
  {
    "id": "506",
    "ts": "31.07.2024 21:31:44",
    "photo": "photos/photo_145@31-07-2024_21-31-44.jpg",
    "text": "小褜芯谐芯写薪褨 胁褨写写邪胁邪谢懈 褌邪泻懈褏 泻褉邪褋褍薪褔懈泻褨胁 馃槏\n袨斜懈写胁邪 褨蟹 薪邪褔懈薪泻芯褞 小薪褨泻械褉褋.\n袛谢褟 褌芯谐芯, 褖芯斜 蟹邪屑芯胁懈褌懈 褍 薪邪褋 褌芯褉褌懈泻-锌懈褕褨褌褜 胁 锌褉懈胁邪褌馃憠\n孝邪泻芯卸 薪邪谐邪写褍褞! 校 薪邪褋 胁 褉械褋褌芯褉邪薪褨 袙懈 屑芯卸械褌械 胁褨写褋胁褟褌泻褍胁邪褌懈 写懈褌褟褔械 褋胁褟褌芯. 袟 泻械薪写褨斜邪褉芯屑, 写懈褌褟褔懈屑 屑械薪褞 褌邪 褎芯褌芯蟹芯薪芯褞! 袙褋褨 写械褌邪谢褨 胁 锌褉懈胁邪褌 馃憠"
  },
  {
    "id": "508",
    "ts": "01.08.2024 08:12:19",
    "photo": "photos/photo_147@01-08-2024_08-12-19.jpg",
    "text": "袙褋褨屑 写芯斜褉芯谐芯 褉邪薪泻褍! 袙褨褌邪褦屑芯 蟹 锌械褉褕懈屑 薪邪胁褔邪谢褜薪懈屑 写薪械屑!"
  },
  {
    "id": "515",
    "ts": "01.08.2024 16:45:20",
    "photo": "photos/photo_148@01-08-2024_16-45-20.jpg",
    "text": "小褜芯谐芯写薪褨 薪邪 谢褨褌薪褨泄 褌械褉邪褋褨 薪邪褕芯谐芯 褉械褋褌芯褉邪薪褍 胁懈 屑芯卸械褌械 薪邪褋芯谢芯写懈褌懈褋褜 胁懈褕褍泻邪薪懈屑懈 写械褋械褉褌邪屑懈!\n袘褨褋泻胁褨褌 袣芯褉芯谢械胁懈 袙褨泻褌芯褉褨褩 蟹 锌芯谢褍薪懈褔薪懈屑 谐邪薪邪褕械屑.\n肖褉邪薪褑褍蟹褜泻懈泄 褌芯褉褌 肖褉械蟹始褦.\n袦褍褋芯胁懈泄 褌芯褉褌 3 褕芯泻芯谢邪写懈.\n袧邪泄褋屑邪褔薪褨褕械 锌械褔懈胁芯-褕芯泻芯谢邪写薪械 屑邪褉屑褍褉芯胁械 褌邪 蟹 M&ms \n孝邪泻芯卸 胁懈 屑芯卸械褌械 芯褋胁褨卸懈褌懈褋褜 写褍卸械 褋屑邪褔薪懈屑懈 泻芯泻"
  },
  {
    "id": "519",
    "ts": "01.08.2024 20:13:43",
    "photo": "photos/photo_152@01-08-2024_20-13-43.jpg",
    "text": "袨褋褜 褌邪泻懈泄 褌芯褉褌懈泻 褋褜芯谐芯写薪褨 蟹褉芯斜懈谢懈 写谢褟 屑邪谢械薪褜泻芯谐芯 小邪褕褨 鈽猴笍\n袙褋械褉械写懈薪褨 3 泻谐 写懈褌褟褔芯褩 薪邪褔懈薪泻懈-薪褨卸薪懈泄 斜邪薪邪薪芯胁懈泄 泻褉械屑 褌邪 胁懈褕薪械胁械 泻芯屑锌芯褌械.\n袛褟泻褍褦屑芯 蟹邪 胁褨写谐褍泻懈!\n袘褍写褜 谢邪褋泻邪, 锌谢邪薪褍泄褌械 褋胁芯褩 蟹邪屑芯胁谢械薪薪褟 蟹邪蟹写邪谢械谐褨写褜, 褖芯斜 屑懈 蟹 胁邪屑懈 胁褋褌懈谐谢懈 蟹邪屑芯胁懈褌懈 写械泻芯褉 褨 屑芯谐谢懈 锌褉懈泄薪褟褌懈 胁邪褕械 蟹邪屑芯胁谢械薪薪褟 鈽猴笍"
  }
]